README.md
setup.py
rb/__init__.py
rb/_rediscommands.py
rb/clients.py
rb/cluster.py
rb/ketama.py
rb/poll.py
rb/promise.py
rb/router.py
rb/testing.py
rb/utils.py
rb3.egg-info/PKG-INFO
rb3.egg-info/SOURCES.txt
rb3.egg-info/dependency_links.txt
rb3.egg-info/requires.txt
rb3.egg-info/top_level.txt