Metadata-Version: 2.1
Name: rb3
Version: 1.8.1a0
Summary: rb3, the redis blaster which support Python 3.7
Home-page: https://github.com/caiyunapp/rb3
Author: Beijing ColorfulClouds Technology Co.,Ltd.
Author-email: admin@caiyunapp.com
License: UNKNOWN
Keywords: Redis rb python3
Platform: UNKNOWN
Classifier: License :: OSI Approved :: Apache Software License
Classifier: Programming Language :: Python
